{
  "name": "OsConfigConfigurationModel",
  "type": "mimModel",
  "contents": [
    {
      "name": "Configuration",
      "type": "mimComponent",
      "contents": [
        {
          "name": "desiredRefreshInterval",
          "type": "mimObject",
          "desired": true,
          "schema": "integer"
        },
        {
          "name": "desiredLocalManagementEnabled",
          "type": "mimObject",
          "desired": true,
          "schema": "boolean"
        },
        {
          "name": "desiredFullLoggingEnabled",
          "type": "mimObject",
          "desired": true,
          "schema": "boolean"
        },
        {
          "name": "desiredCommandLoggingEnabled",
          "type": "mimObject",
          "desired": true,
          "schema": "boolean"
        },
        {
          "name": "desiredIotHubManagementEnabled",
          "type": "mimObject",
          "desired": true,
          "schema": "boolean"
        },
        {
          "name": "desiredIotHubProtocol",
          "type": "mimObject",
          "desired": true,
          "schema": {
            "type": "enum",
            "valueSchema": "string",
            "enumValues": [
              {
                "name": "auto",
                "enumValue": "auto"
              },
              {
                "name": "mqtt",
                "enumValue": "mqtt"
              },
              {
                "name": "mqttWebSocket",
                "enumValue": "mqttWebSocket"
              }
            ]
          }
        },
        {
          "name": "desiredGitManagementEnabled",
          "type": "mimObject",
          "desired": true,
          "schema": "boolean"
        },
        {
          "name": "desiredGitBranch",
          "type": "mimObject",
          "desired": true,
          "schema": "string"
        },
        {
          "name": "modelVersion",
          "type": "mimObject",
          "desired": false,
          "schema": "integer"
        },
        {
          "name": "refreshInterval",
          "type": "mimObject",
          "desired": false,
          "schema": "integer"
        },
        {
          "name": "localManagementEnabled",
          "type": "mimObject",
          "desired": false,
          "schema": "boolean"
        },
        {
          "name": "fullLoggingEnabled",
          "type": "mimObject",
          "desired": false,
          "schema": "boolean"
        },
        {
          "name": "commandLoggingEnabled",
          "type": "mimObject",
          "desired": false,
          "schema": "boolean"
        },
        {
          "name": "iotHubManagamentEnabled",
          "type": "mimObject",
          "desired": false,
          "schema": "boolean"
        },
        {
          "name": "iotHubProtocol",
          "type": "mimObject",
          "desired": false,
          "schema": {
            "type": "enum",
            "valueSchema": "string",
            "enumValues": [
              {
                "name": "auto",
                "enumValue": "auto"
              },
              {
                "name": "mqtt",
                "enumValue": "mqtt"
              },
              {
                "name": "mqttWebSocket",
                "enumValue": "mqttWebSocket"
              }
            ]
          }
        },
        {
          "name": "gitManagementEnabled",
          "type": "mimObject",
          "desired": false,
          "schema": "boolean"
        },
        {
          "name": "gitBranch",
          "type": "mimObject",
          "desired": false,
          "schema": "string"
        }
      ]
    }
  ]
}
