{
  "name": "TpmModel",
  "type": "mimModel",
  "contents": [
    {
      "name": "Tpm",
      "type": "mimComponent",
      "contents": [
        {
          "name": "tpmStatus",
          "type": "mimObject",
          "desired": false,
          "schema": {
             "type": "enum",
             "valueSchema": "integer",
             "enumValues": [
               {
                 "name": "unknown",
                 "enumValue": 0
               },
               {
                 "name": "tpmDetected",
                 "enumValue": 1
               },
               {
                 "name": "tpmNotDetected",
                 "enumValue": 2
               }
             ]
           }
        },
        {
          "name": "tpmVersion",
          "type": "mimObject",
          "desired": false,
          "schema": "string"
        },
        {
          "name": "tpmManufacturer",
          "type": "mimObject",
          "desired": false,
          "schema": "string"
        }
      ]
    }
  ]
}
