{
  "$schema": "http://json-schema.org/draft-07/schema#",
  "definitions": {
    "audit": {
      "anyOf": [
        {
          "type": "object",
          "required": [
            "MountPointExists"
          ],
          "additionalProperties": false,
          "properties": {
            "MountPointExists": {
              "type": "object",
              "required": [
                "mountPoint"
              ],
              "additionalProperties": false,
              "properties": {
                "mountPoint": {
                  "type": "string",
                  "description": "Mount point to check"
                }
              }
            }
          }
        }
      ]
    },
    "remediation": {
      "anyOf": []
    }
  }
}
